zimzim/__init__.py
zimzim/hello.py
hellodum-0.0.5.dist-info/METADATA
hellodum-0.0.5.dist-info/WHEEL
hellodum-0.0.5.dist-info/top_level.txt
hellodum-0.0.5.dist-info/RECORD
