Metadata-Version: 2.1
Name: hellodum
Version: 0.0.5
Summary: A Simple Hello package, bro!
Author: Huzaifa
Author-email: huzaifat65@outlook.com
Classifier: Intended Audience :: Developers
Classifier: Programming Language :: Python :: 3
Classifier: Operating System :: OS Independent
Classifier: 
Requires-Dist: numpy
